CHANGELOG
LICENSE
MANIFEST.in
README
setup.py
pycsse/__init__.py
pycsse/pycsse.py
pycsse.egg-info/PKG-INFO
pycsse.egg-info/SOURCES.txt
pycsse.egg-info/dependency_links.txt
pycsse.egg-info/not-zip-safe
pycsse.egg-info/requires.txt
pycsse.egg-info/top_level.txt