Metadata-Version: 1.0
Name: pycsse
Version: 0.2.0
Summary: CSSe to CSS export tool.
Home-page: http://github.com/idlesign/pycsse
Author: Igor 'idle sign' Starikov
Author-email: idlesign@yandex.ru
License: UNKNOWN
Platform: UNKNOWN
Classifier: Development Status :: 3 - Alpha
Classifier: Environment :: Console
Classifier: Intended Audience :: Developers
Classifier: License :: OSI Approved :: BSD License
Classifier: Operating System :: OS Independent
Classifier: Programming Language :: Python :: 2.5
Classifier: Topic :: Internet :: WWW/HTTP
